{
  "version": "6",
  "dialect": "sqlite",
  "id": "8908a602-5ce0-4ebd-afc8-26497055c051",
  "prevId": "e370f1be-778d-4a25-a5af-cc48ed9fac9c",
  "tables": {
    "account": {
      "name": "account",
      "columns": {
        "id": {
          "name": "id",
          "type": "text",
          "primaryKey": true,
          "notNull": true,
          "autoincrement": false
        },
        "account_id": {
          "name": "account_id",
          "type": "text",
          "primaryKey": false,
          "notNull": true,
          "autoincrement": false
        },
        "provider_id": {
          "name": "provider_id",
          "type": "text",
          "primaryKey": false,
          "notNull": true,
          "autoincrement": false
        },
        "user_id": {
          "name": "user_id",
          "type": "text",
          "primaryKey": false,
          "notNull": true,
          "autoincrement": false
        },
        "access_token": {
          "name": "access_token",
          "type": "text",
          "primaryKey": false,
          "notNull": false,
          "autoincrement": false
        },
        "refresh_token": {
          "name": "refresh_token",
          "type": "text",
          "primaryKey": false,
          "notNull": false,
          "autoincrement": false
        },
        "id_token": {
          "name": "id_token",
          "type": "text",
          "primaryKey": false,
          "notNull": false,
          "autoincrement": false
        },
        "access_token_expires_at": {
          "name": "access_token_expires_at",
          "type": "integer",
          "primaryKey": false,
          "notNull": false,
          "autoincrement": false
        },
        "refresh_token_expires_at": {
          "name": "refresh_token_expires_at",
          "type": "integer",
          "primaryKey": false,
          "notNull": false,
          "autoincrement": false
        },
        "scope": {
          "name": "scope",
          "type": "text",
          "primaryKey": false,
          "notNull": false,
          "autoincrement": false
        },
        "password": {
          "name": "password",
          "type": "text",
          "primaryKey": false,
          "notNull": false,
          "autoincrement": false
        },
        "created_at": {
          "name": "created_at",
          "type": "integer",
          "primaryKey": false,
          "notNull": true,
          "autoincrement": false,
          "default": "(cast(unixepoch('subsecond') * 1000 as integer))"
        },
        "updated_at": {
          "name": "updated_at",
          "type": "integer",
          "primaryKey": false,
          "notNull": true,
          "autoincrement": false
        }
      },
      "indexes": {
        "account_userId_idx": {
          "name": "account_userId_idx",
          "columns": [
            "user_id"
          ],
          "isUnique": false
        }
      },
      "foreignKeys": {
        "account_user_id_user_id_fk": {
          "name": "account_user_id_user_id_fk",
          "tableFrom": "account",
          "tableTo": "user",
          "columnsFrom": [
            "user_id"
          ],
          "columnsTo": [
            "id"
          ],
          "onDelete": "cascade",
          "onUpdate": "no action"
        }
      },
      "compositePrimaryKeys": {},
      "uniqueConstraints": {},
      "checkConstraints": {}
    },
    "oauthAccessToken": {
      "name": "oauthAccessToken",
      "columns": {
        "id": {
          "name": "id",
          "type": "text",
          "primaryKey": true,
          "notNull": true,
          "autoincrement": false
        },
        "token": {
          "name": "token",
          "type": "text",
          "primaryKey": false,
          "notNull": true,
          "autoincrement": false
        },
        "client_id": {
          "name": "client_id",
          "type": "text",
          "primaryKey": false,
          "notNull": true,
          "autoincrement": false
        },
        "session_id": {
          "name": "session_id",
          "type": "text",
          "primaryKey": false,
          "notNull": false,
          "autoincrement": false
        },
        "refresh_id": {
          "name": "refresh_id",
          "type": "text",
          "primaryKey": false,
          "notNull": false,
          "autoincrement": false
        },
        "user_id": {
          "name": "user_id",
          "type": "text",
          "primaryKey": false,
          "notNull": false,
          "autoincrement": false
        },
        "reference_id": {
          "name": "reference_id",
          "type": "text",
          "primaryKey": false,
          "notNull": false,
          "autoincrement": false
        },
        "scopes": {
          "name": "scopes",
          "type": "text",
          "primaryKey": false,
          "notNull": true,
          "autoincrement": false,
          "default": "'[]'"
        },
        "created_at": {
          "name": "created_at",
          "type": "integer",
          "primaryKey": false,
          "notNull": true,
          "autoincrement": false,
          "default": "(cast(unixepoch('subsecond') * 1000 as integer))"
        },
        "expires_at": {
          "name": "expires_at",
          "type": "integer",
          "primaryKey": false,
          "notNull": true,
          "autoincrement": false
        }
      },
      "indexes": {
        "oauthAccessToken_token_unique": {
          "name": "oauthAccessToken_token_unique",
          "columns": [
            "token"
          ],
          "isUnique": true
        },
        "oauthAccessToken_clientId_idx": {
          "name": "oauthAccessToken_clientId_idx",
          "columns": [
            "client_id"
          ],
          "isUnique": false
        },
        "oauthAccessToken_userId_idx": {
          "name": "oauthAccessToken_userId_idx",
          "columns": [
            "user_id"
          ],
          "isUnique": false
        },
        "oauthAccessToken_refreshId_idx": {
          "name": "oauthAccessToken_refreshId_idx",
          "columns": [
            "refresh_id"
          ],
          "isUnique": false
        }
      },
      "foreignKeys": {
        "oauthAccessToken_client_id_oauthClient_client_id_fk": {
          "name": "oauthAccessToken_client_id_oauthClient_client_id_fk",
          "tableFrom": "oauthAccessToken",
          "tableTo": "oauthClient",
          "columnsFrom": [
            "client_id"
          ],
          "columnsTo": [
            "client_id"
          ],
          "onDelete": "cascade",
          "onUpdate": "no action"
        },
        "oauthAccessToken_session_id_session_id_fk": {
          "name": "oauthAccessToken_session_id_session_id_fk",
          "tableFrom": "oauthAccessToken",
          "tableTo": "session",
          "columnsFrom": [
            "session_id"
          ],
          "columnsTo": [
            "id"
          ],
          "onDelete": "set null",
          "onUpdate": "no action"
        },
        "oauthAccessToken_refresh_id_oauthRefreshToken_id_fk": {
          "name": "oauthAccessToken_refresh_id_oauthRefreshToken_id_fk",
          "tableFrom": "oauthAccessToken",
          "tableTo": "oauthRefreshToken",
          "columnsFrom": [
            "refresh_id"
          ],
          "columnsTo": [
            "id"
          ],
          "onDelete": "set null",
          "onUpdate": "no action"
        },
        "oauthAccessToken_user_id_user_id_fk": {
          "name": "oauthAccessToken_user_id_user_id_fk",
          "tableFrom": "oauthAccessToken",
          "tableTo": "user",
          "columnsFrom": [
            "user_id"
          ],
          "columnsTo": [
            "id"
          ],
          "onDelete": "set null",
          "onUpdate": "no action"
        }
      },
      "compositePrimaryKeys": {},
      "uniqueConstraints": {},
      "checkConstraints": {}
    },
    "oauthClient": {
      "name": "oauthClient",
      "columns": {
        "id": {
          "name": "id",
          "type": "text",
          "primaryKey": true,
          "notNull": true,
          "autoincrement": false
        },
        "client_id": {
          "name": "client_id",
          "type": "text",
          "primaryKey": false,
          "notNull": true,
          "autoincrement": false
        },
        "client_secret": {
          "name": "client_secret",
          "type": "text",
          "primaryKey": false,
          "notNull": false,
          "autoincrement": false
        },
        "disabled": {
          "name": "disabled",
          "type": "integer",
          "primaryKey": false,
          "notNull": true,
          "autoincrement": false,
          "default": false
        },
        "skip_consent": {
          "name": "skip_consent",
          "type": "integer",
          "primaryKey": false,
          "notNull": true,
          "autoincrement": false,
          "default": false
        },
        "enable_end_session": {
          "name": "enable_end_session",
          "type": "integer",
          "primaryKey": false,
          "notNull": true,
          "autoincrement": false,
          "default": false
        },
        "scopes": {
          "name": "scopes",
          "type": "text",
          "primaryKey": false,
          "notNull": true,
          "autoincrement": false,
          "default": "'[]'"
        },
        "user_id": {
          "name": "user_id",
          "type": "text",
          "primaryKey": false,
          "notNull": false,
          "autoincrement": false
        },
        "reference_id": {
          "name": "reference_id",
          "type": "text",
          "primaryKey": false,
          "notNull": false,
          "autoincrement": false
        },
        "created_at": {
          "name": "created_at",
          "type": "integer",
          "primaryKey": false,
          "notNull": true,
          "autoincrement": false,
          "default": "(cast(unixepoch('subsecond') * 1000 as integer))"
        },
        "updated_at": {
          "name": "updated_at",
          "type": "integer",
          "primaryKey": false,
          "notNull": true,
          "autoincrement": false,
          "default": "(cast(unixepoch('subsecond') * 1000 as integer))"
        },
        "name": {
          "name": "name",
          "type": "text",
          "primaryKey": false,
          "notNull": false,
          "autoincrement": false
        },
        "uri": {
          "name": "uri",
          "type": "text",
          "primaryKey": false,
          "notNull": false,
          "autoincrement": false
        },
        "icon": {
          "name": "icon",
          "type": "text",
          "primaryKey": false,
          "notNull": false,
          "autoincrement": false
        },
        "contacts": {
          "name": "contacts",
          "type": "text",
          "primaryKey": false,
          "notNull": true,
          "autoincrement": false,
          "default": "'[]'"
        },
        "tos": {
          "name": "tos",
          "type": "text",
          "primaryKey": false,
          "notNull": false,
          "autoincrement": false
        },
        "policy": {
          "name": "policy",
          "type": "text",
          "primaryKey": false,
          "notNull": false,
          "autoincrement": false
        },
        "software_id": {
          "name": "software_id",
          "type": "text",
          "primaryKey": false,
          "notNull": false,
          "autoincrement": false
        },
        "software_version": {
          "name": "software_version",
          "type": "text",
          "primaryKey": false,
          "notNull": false,
          "autoincrement": false
        },
        "software_statement": {
          "name": "software_statement",
          "type": "text",
          "primaryKey": false,
          "notNull": false,
          "autoincrement": false
        },
        "redirect_uris": {
          "name": "redirect_uris",
          "type": "text",
          "primaryKey": false,
          "notNull": true,
          "autoincrement": false
        },
        "token_endpoint_auth_method": {
          "name": "token_endpoint_auth_method",
          "type": "text",
          "primaryKey": false,
          "notNull": false,
          "autoincrement": false
        },
        "grant_types": {
          "name": "grant_types",
          "type": "text",
          "primaryKey": false,
          "notNull": true,
          "autoincrement": false,
          "default": "'[]'"
        },
        "response_types": {
          "name": "response_types",
          "type": "text",
          "primaryKey": false,
          "notNull": true,
          "autoincrement": false,
          "default": "'[]'"
        },
        "public": {
          "name": "public",
          "type": "integer",
          "primaryKey": false,
          "notNull": true,
          "autoincrement": false,
          "default": false
        },
        "type": {
          "name": "type",
          "type": "text",
          "primaryKey": false,
          "notNull": false,
          "autoincrement": false
        },
        "metadata": {
          "name": "metadata",
          "type": "text",
          "primaryKey": false,
          "notNull": false,
          "autoincrement": false
        }
      },
      "indexes": {
        "oauthClient_client_id_unique": {
          "name": "oauthClient_client_id_unique",
          "columns": [
            "client_id"
          ],
          "isUnique": true
        },
        "oauthClient_userId_idx": {
          "name": "oauthClient_userId_idx",
          "columns": [
            "user_id"
          ],
          "isUnique": false
        },
        "oauthClient_referenceId_idx": {
          "name": "oauthClient_referenceId_idx",
          "columns": [
            "reference_id"
          ],
          "isUnique": false
        }
      },
      "foreignKeys": {
        "oauthClient_user_id_user_id_fk": {
          "name": "oauthClient_user_id_user_id_fk",
          "tableFrom": "oauthClient",
          "tableTo": "user",
          "columnsFrom": [
            "user_id"
          ],
          "columnsTo": [
            "id"
          ],
          "onDelete": "set null",
          "onUpdate": "no action"
        }
      },
      "compositePrimaryKeys": {},
      "uniqueConstraints": {},
      "checkConstraints": {}
    },
    "oauthConsent": {
      "name": "oauthConsent",
      "columns": {
        "id": {
          "name": "id",
          "type": "text",
          "primaryKey": true,
          "notNull": true,
          "autoincrement": false
        },
        "user_id": {
          "name": "user_id",
          "type": "text",
          "primaryKey": false,
          "notNull": true,
          "autoincrement": false
        },
        "client_id": {
          "name": "client_id",
          "type": "text",
          "primaryKey": false,
          "notNull": true,
          "autoincrement": false
        },
        "reference_id": {
          "name": "reference_id",
          "type": "text",
          "primaryKey": false,
          "notNull": false,
          "autoincrement": false
        },
        "scopes": {
          "name": "scopes",
          "type": "text",
          "primaryKey": false,
          "notNull": true,
          "autoincrement": false
        },
        "created_at": {
          "name": "created_at",
          "type": "integer",
          "primaryKey": false,
          "notNull": true,
          "autoincrement": false,
          "default": "(cast(unixepoch('subsecond') * 1000 as integer))"
        },
        "updated_at": {
          "name": "updated_at",
          "type": "integer",
          "primaryKey": false,
          "notNull": true,
          "autoincrement": false,
          "default": "(cast(unixepoch('subsecond') * 1000 as integer))"
        }
      },
      "indexes": {
        "oauthConsent_userId_idx": {
          "name": "oauthConsent_userId_idx",
          "columns": [
            "user_id"
          ],
          "isUnique": false
        },
        "oauthConsent_clientId_idx": {
          "name": "oauthConsent_clientId_idx",
          "columns": [
            "client_id"
          ],
          "isUnique": false
        }
      },
      "foreignKeys": {
        "oauthConsent_user_id_user_id_fk": {
          "name": "oauthConsent_user_id_user_id_fk",
          "tableFrom": "oauthConsent",
          "tableTo": "user",
          "columnsFrom": [
            "user_id"
          ],
          "columnsTo": [
            "id"
          ],
          "onDelete": "cascade",
          "onUpdate": "no action"
        },
        "oauthConsent_client_id_oauthClient_client_id_fk": {
          "name": "oauthConsent_client_id_oauthClient_client_id_fk",
          "tableFrom": "oauthConsent",
          "tableTo": "oauthClient",
          "columnsFrom": [
            "client_id"
          ],
          "columnsTo": [
            "client_id"
          ],
          "onDelete": "cascade",
          "onUpdate": "no action"
        }
      },
      "compositePrimaryKeys": {},
      "uniqueConstraints": {},
      "checkConstraints": {}
    },
    "oauthRefreshToken": {
      "name": "oauthRefreshToken",
      "columns": {
        "id": {
          "name": "id",
          "type": "text",
          "primaryKey": true,
          "notNull": true,
          "autoincrement": false
        },
        "token": {
          "name": "token",
          "type": "text",
          "primaryKey": false,
          "notNull": true,
          "autoincrement": false
        },
        "client_id": {
          "name": "client_id",
          "type": "text",
          "primaryKey": false,
          "notNull": true,
          "autoincrement": false
        },
        "session_id": {
          "name": "session_id",
          "type": "text",
          "primaryKey": false,
          "notNull": false,
          "autoincrement": false
        },
        "user_id": {
          "name": "user_id",
          "type": "text",
          "primaryKey": false,
          "notNull": false,
          "autoincrement": false
        },
        "reference_id": {
          "name": "reference_id",
          "type": "text",
          "primaryKey": false,
          "notNull": false,
          "autoincrement": false
        },
        "scopes": {
          "name": "scopes",
          "type": "text",
          "primaryKey": false,
          "notNull": true,
          "autoincrement": false,
          "default": "'[]'"
        },
        "revoked": {
          "name": "revoked",
          "type": "integer",
          "primaryKey": false,
          "notNull": false,
          "autoincrement": false
        },
        "created_at": {
          "name": "created_at",
          "type": "integer",
          "primaryKey": false,
          "notNull": true,
          "autoincrement": false,
          "default": "(cast(unixepoch('subsecond') * 1000 as integer))"
        },
        "expires_at": {
          "name": "expires_at",
          "type": "integer",
          "primaryKey": false,
          "notNull": true,
          "autoincrement": false
        }
      },
      "indexes": {
        "oauthRefreshToken_token_unique": {
          "name": "oauthRefreshToken_token_unique",
          "columns": [
            "token"
          ],
          "isUnique": true
        },
        "oauthRefreshToken_clientId_idx": {
          "name": "oauthRefreshToken_clientId_idx",
          "columns": [
            "client_id"
          ],
          "isUnique": false
        },
        "oauthRefreshToken_userId_idx": {
          "name": "oauthRefreshToken_userId_idx",
          "columns": [
            "user_id"
          ],
          "isUnique": false
        }
      },
      "foreignKeys": {
        "oauthRefreshToken_client_id_oauthClient_client_id_fk": {
          "name": "oauthRefreshToken_client_id_oauthClient_client_id_fk",
          "tableFrom": "oauthRefreshToken",
          "tableTo": "oauthClient",
          "columnsFrom": [
            "client_id"
          ],
          "columnsTo": [
            "client_id"
          ],
          "onDelete": "cascade",
          "onUpdate": "no action"
        },
        "oauthRefreshToken_session_id_session_id_fk": {
          "name": "oauthRefreshToken_session_id_session_id_fk",
          "tableFrom": "oauthRefreshToken",
          "tableTo": "session",
          "columnsFrom": [
            "session_id"
          ],
          "columnsTo": [
            "id"
          ],
          "onDelete": "set null",
          "onUpdate": "no action"
        },
        "oauthRefreshToken_user_id_user_id_fk": {
          "name": "oauthRefreshToken_user_id_user_id_fk",
          "tableFrom": "oauthRefreshToken",
          "tableTo": "user",
          "columnsFrom": [
            "user_id"
          ],
          "columnsTo": [
            "id"
          ],
          "onDelete": "set null",
          "onUpdate": "no action"
        }
      },
      "compositePrimaryKeys": {},
      "uniqueConstraints": {},
      "checkConstraints": {}
    },
    "session": {
      "name": "session",
      "columns": {
        "id": {
          "name": "id",
          "type": "text",
          "primaryKey": true,
          "notNull": true,
          "autoincrement": false
        },
        "expires_at": {
          "name": "expires_at",
          "type": "integer",
          "primaryKey": false,
          "notNull": true,
          "autoincrement": false
        },
        "token": {
          "name": "token",
          "type": "text",
          "primaryKey": false,
          "notNull": true,
          "autoincrement": false
        },
        "created_at": {
          "name": "created_at",
          "type": "integer",
          "primaryKey": false,
          "notNull": true,
          "autoincrement": false,
          "default": "(cast(unixepoch('subsecond') * 1000 as integer))"
        },
        "updated_at": {
          "name": "updated_at",
          "type": "integer",
          "primaryKey": false,
          "notNull": true,
          "autoincrement": false
        },
        "ip_address": {
          "name": "ip_address",
          "type": "text",
          "primaryKey": false,
          "notNull": false,
          "autoincrement": false
        },
        "user_agent": {
          "name": "user_agent",
          "type": "text",
          "primaryKey": false,
          "notNull": false,
          "autoincrement": false
        },
        "user_id": {
          "name": "user_id",
          "type": "text",
          "primaryKey": false,
          "notNull": true,
          "autoincrement": false
        }
      },
      "indexes": {
        "session_token_unique": {
          "name": "session_token_unique",
          "columns": [
            "token"
          ],
          "isUnique": true
        },
        "session_userId_idx": {
          "name": "session_userId_idx",
          "columns": [
            "user_id"
          ],
          "isUnique": false
        }
      },
      "foreignKeys": {
        "session_user_id_user_id_fk": {
          "name": "session_user_id_user_id_fk",
          "tableFrom": "session",
          "tableTo": "user",
          "columnsFrom": [
            "user_id"
          ],
          "columnsTo": [
            "id"
          ],
          "onDelete": "cascade",
          "onUpdate": "no action"
        }
      },
      "compositePrimaryKeys": {},
      "uniqueConstraints": {},
      "checkConstraints": {}
    },
    "user": {
      "name": "user",
      "columns": {
        "id": {
          "name": "id",
          "type": "text",
          "primaryKey": true,
          "notNull": true,
          "autoincrement": false
        },
        "name": {
          "name": "name",
          "type": "text",
          "primaryKey": false,
          "notNull": true,
          "autoincrement": false
        },
        "email": {
          "name": "email",
          "type": "text",
          "primaryKey": false,
          "notNull": true,
          "autoincrement": false
        },
        "email_verified": {
          "name": "email_verified",
          "type": "integer",
          "primaryKey": false,
          "notNull": true,
          "autoincrement": false,
          "default": false
        },
        "image": {
          "name": "image",
          "type": "text",
          "primaryKey": false,
          "notNull": false,
          "autoincrement": false
        },
        "role": {
          "name": "role",
          "type": "text",
          "primaryKey": false,
          "notNull": false,
          "autoincrement": false
        },
        "created_at": {
          "name": "created_at",
          "type": "integer",
          "primaryKey": false,
          "notNull": true,
          "autoincrement": false,
          "default": "(cast(unixepoch('subsecond') * 1000 as integer))"
        },
        "updated_at": {
          "name": "updated_at",
          "type": "integer",
          "primaryKey": false,
          "notNull": true,
          "autoincrement": false,
          "default": "(cast(unixepoch('subsecond') * 1000 as integer))"
        }
      },
      "indexes": {
        "user_email_unique": {
          "name": "user_email_unique",
          "columns": [
            "email"
          ],
          "isUnique": true
        }
      },
      "foreignKeys": {},
      "compositePrimaryKeys": {},
      "uniqueConstraints": {},
      "checkConstraints": {}
    },
    "verification": {
      "name": "verification",
      "columns": {
        "id": {
          "name": "id",
          "type": "text",
          "primaryKey": true,
          "notNull": true,
          "autoincrement": false
        },
        "identifier": {
          "name": "identifier",
          "type": "text",
          "primaryKey": false,
          "notNull": true,
          "autoincrement": false
        },
        "value": {
          "name": "value",
          "type": "text",
          "primaryKey": false,
          "notNull": true,
          "autoincrement": false
        },
        "expires_at": {
          "name": "expires_at",
          "type": "integer",
          "primaryKey": false,
          "notNull": true,
          "autoincrement": false
        },
        "created_at": {
          "name": "created_at",
          "type": "integer",
          "primaryKey": false,
          "notNull": true,
          "autoincrement": false,
          "default": "(cast(unixepoch('subsecond') * 1000 as integer))"
        },
        "updated_at": {
          "name": "updated_at",
          "type": "integer",
          "primaryKey": false,
          "notNull": true,
          "autoincrement": false,
          "default": "(cast(unixepoch('subsecond') * 1000 as integer))"
        }
      },
      "indexes": {
        "verification_identifier_idx": {
          "name": "verification_identifier_idx",
          "columns": [
            "identifier"
          ],
          "isUnique": false
        }
      },
      "foreignKeys": {},
      "compositePrimaryKeys": {},
      "uniqueConstraints": {},
      "checkConstraints": {}
    }
  },
  "views": {},
  "enums": {},
  "_meta": {
    "schemas": {},
    "tables": {},
    "columns": {}
  },
  "internal": {
    "indexes": {}
  }
}